CcnpShiyanShouceWuming/README.md
CcnpShiyanShouceWuming/__init__.py
CcnpShiyanShouceWuming/__main__.py
CcnpShiyanShouceWuming/file.pdf
CcnpShiyanShouceWuming/index.html
ccnp_shiyan_shouce_wuming-2024.3.5.0.dist-info/METADATA
ccnp_shiyan_shouce_wuming-2024.3.5.0.dist-info/WHEEL
ccnp_shiyan_shouce_wuming-2024.3.5.0.dist-info/entry_points.txt
ccnp_shiyan_shouce_wuming-2024.3.5.0.dist-info/top_level.txt
ccnp_shiyan_shouce_wuming-2024.3.5.0.dist-info/RECORD
